programasweights/__init__.py
programasweights/artifacts.py
programasweights/compiler/__init__.py
programasweights/compiler/dummy.py
programasweights/runtime/__init__.py
programasweights/runtime/interpreter.py
programasweights-0.1.1.dist-info/METADATA
programasweights-0.1.1.dist-info/WHEEL
programasweights-0.1.1.dist-info/entry_points.txt
programasweights-0.1.1.dist-info/RECORD
